shepherd/__init__.py
shepherd/shepherd_launch.py
shepherd_shrine-0.1.4.dist-info/licenses/LICENSE
shepherd_shrine-0.1.4.dist-info/METADATA
shepherd_shrine-0.1.4.dist-info/WHEEL
shepherd_shrine-0.1.4.dist-info/entry_points.txt
shepherd_shrine-0.1.4.dist-info/top_level.txt
shepherd_shrine-0.1.4.dist-info/RECORD
