Metadata-Version: 2.4
Name: shepherd-shrine
Version: 0.1.4
Summary: Shepherd's Shrine dashboard generator
Author: ChaosEngine
License: MIT License
Classifier: Programming Language :: Python :: 3
Classifier: Programming Language :: Python :: 3 :: Only
Classifier: Programming Language :: Python :: 3.12
Classifier: License :: OSI Approved :: MIT License
Classifier: Operating System :: OS Independent
Requires-Python: >=3.12
License-File: LICENSE
Dynamic: license-file
